libucxx/GIT_COMMIT
libucxx/VERSION
libucxx/__init__.py
libucxx/_version.py
libucxx/load.py
libucxx/include/ucxx/address.h
libucxx/include/ucxx/api.h
libucxx/include/ucxx/buffer.h
libucxx/include/ucxx/component.h
libucxx/include/ucxx/config.h
libucxx/include/ucxx/constructors.h
libucxx/include/ucxx/context.h
libucxx/include/ucxx/delayed_submission.h
libucxx/include/ucxx/endpoint.h
libucxx/include/ucxx/exception.h
libucxx/include/ucxx/future.h
libucxx/include/ucxx/header.h
libucxx/include/ucxx/inflight_requests.h
libucxx/include/ucxx/listener.h
libucxx/include/ucxx/log.h
libucxx/include/ucxx/memory_handle.h
libucxx/include/ucxx/notifier.h
libucxx/include/ucxx/remote_key.h
libucxx/include/ucxx/request.h
libucxx/include/ucxx/request_am.h
libucxx/include/ucxx/request_data.h
libucxx/include/ucxx/request_endpoint_close.h
libucxx/include/ucxx/request_flush.h
libucxx/include/ucxx/request_helper.h
libucxx/include/ucxx/request_mem.h
libucxx/include/ucxx/request_stream.h
libucxx/include/ucxx/request_tag.h
libucxx/include/ucxx/request_tag_multi.h
libucxx/include/ucxx/tag_probe.h
libucxx/include/ucxx/typedefs.h
libucxx/include/ucxx/worker.h
libucxx/include/ucxx/worker_progress_thread.h
libucxx/include/ucxx/experimental/context_builder.h
libucxx/include/ucxx/experimental/worker_builder.h
libucxx/include/ucxx/internal/request_am.h
libucxx/include/ucxx/utils/callback_notifier.h
libucxx/include/ucxx/utils/file_descriptor.h
libucxx/include/ucxx/utils/python.h
libucxx/include/ucxx/utils/sockaddr.h
libucxx/include/ucxx/utils/ucx.h
libucxx/lib64/libucxx.so
libucxx/lib64/cmake/ucxx/ucxx-config-version.cmake
libucxx/lib64/cmake/ucxx/ucxx-config.cmake
libucxx/lib64/cmake/ucxx/ucxx-dependencies.cmake
libucxx/lib64/cmake/ucxx/ucxx-targets-release.cmake
libucxx/lib64/cmake/ucxx/ucxx-targets.cmake
libucxx_cu13-0.47.0.dist-info/METADATA
libucxx_cu13-0.47.0.dist-info/WHEEL
libucxx_cu13-0.47.0.dist-info/entry_points.txt
libucxx_cu13-0.47.0.dist-info/RECORD
libucxx_cu13-0.47.0.dist-info/licenses/LICENSE
